README.md
setup.cfg
setup.py
bsdemo/Bs demo.py
bsdemo/__init__.py
bsdemo.egg-info/PKG-INFO
bsdemo.egg-info/SOURCES.txt
bsdemo.egg-info/dependency_links.txt
bsdemo.egg-info/top_level.txt