Metadata-Version: 2.1
Name: bsdemo
Version: 0.0.1
Summary: book search
Home-page: https://github.com/jorca24/Book-search-1.1.1.git
Author: jorca
Author-email: junehuang2016@163.com
